thisisneat/__init__.py
thisisneat/_version.py
thisisneat/py.typed
thisisneat/core/__init__.py
thisisneat/core/_config.py
thisisneat/core/_constants.py
thisisneat/core/_shared.py
thisisneat/core/_client/__init__.py
thisisneat/core/_client/_api_client.py
thisisneat/core/_client/testing.py
thisisneat/core/_client/_api/__init__.py
thisisneat/core/_client/_api/data_modeling_loaders.py
thisisneat/core/_client/_api/neat_instances.py
thisisneat/core/_client/_api/schema.py
thisisneat/core/_client/_api/statistics.py
thisisneat/core/_client/data_classes/__init__.py
thisisneat/core/_client/data_classes/data_modeling.py
thisisneat/core/_client/data_classes/neat_sequence.py
thisisneat/core/_client/data_classes/schema.py
thisisneat/core/_client/data_classes/statistics.py
thisisneat/core/_data_model/__init__.py
thisisneat/core/_data_model/_constants.py
thisisneat/core/_data_model/_shared.py
thisisneat/core/_data_model/analysis/__init__.py
thisisneat/core/_data_model/analysis/_base.py
thisisneat/core/_data_model/catalog/__init__.py
thisisneat/core/_data_model/catalog/classic_model.xlsx
thisisneat/core/_data_model/catalog/conceptual-imf-data-model.xlsx
thisisneat/core/_data_model/catalog/hello_world_pump.xlsx
thisisneat/core/_data_model/exporters/__init__.py
thisisneat/core/_data_model/exporters/_base.py
thisisneat/core/_data_model/exporters/_data_model2dms.py
thisisneat/core/_data_model/exporters/_data_model2excel.py
thisisneat/core/_data_model/exporters/_data_model2instance_template.py
thisisneat/core/_data_model/exporters/_data_model2ontology.py
thisisneat/core/_data_model/exporters/_data_model2yaml.py
thisisneat/core/_data_model/importers/__init__.py
thisisneat/core/_data_model/importers/_base.py
thisisneat/core/_data_model/importers/_base_file_reader.py
thisisneat/core/_data_model/importers/_dict2data_model.py
thisisneat/core/_data_model/importers/_dms2data_model.py
thisisneat/core/_data_model/importers/_graph2data_model.py
thisisneat-0.2.2.dist-info/METADATA
thisisneat-0.2.2.dist-info/WHEEL
thisisneat-0.2.2.dist-info/licenses/LICENSE
thisisneat-0.2.2.dist-info/RECORD
