Metadata-Version: 2.4
Name: thisisneat
Version: 0.2.2
Summary: Knowledge graph transformation
Project-URL: Documentation, https://thisisneat.io/
Project-URL: Homepage, https://thisisneat.io/
Project-URL: GitHub, https://github.com/thisisneat-io/thisisneat
Project-URL: Changelog, https://github.com/thisisneat-io/thisisneat/releases
Author-email: Nikola Vasiljevic <nikola.vasiljevic@cognite.com>, Anders Albert <anders.albert@cognite.com>
License-Expression: Apache-2.0
License-File: LICENSE
Requires-Python: >=3.10
Requires-Dist: backports-strenum<2.0.0,>=1.2; python_version < '3.11'
Requires-Dist: cognite-sdk<8.0.0,>=7.83.0
Requires-Dist: elementpath<5.0.0,>=4.0.0
Requires-Dist: exceptiongroup<2.0.0,>=1.1.3; python_version < '3.11'
Requires-Dist: jsonpath-python<2.0.0,>=1.0.6
Requires-Dist: mixpanel<5.0.0,>=4.10.1
Requires-Dist: networkx<4.0.0,>=3.4.2
Requires-Dist: openpyxl<4.0.0,>=3.0.10
Requires-Dist: packaging>=22.0
Requires-Dist: pandas<3.0.0,>=1.5.3
Requires-Dist: pydantic<3.0.0,>=2.0.0
Requires-Dist: pyshacl>=0.30.1
Requires-Dist: pyvis<1.0.0,>=0.3.2
Requires-Dist: pyyaml<7.0.0,>=6.0.1
Requires-Dist: rdflib<8.0.0,>=7.0.0
Requires-Dist: requests<3.0.0,>=2.28.1
Requires-Dist: rich[jupyter]<14.0.0,>=13.7.1
Requires-Dist: tomli<3.0.0,>=2.0.1; python_version < '3.11'
Requires-Dist: typing-extensions<5.0.0,>=4.8.0; python_version < '3.11'
Requires-Dist: urllib3<3.0.0,>=1.26.15
Provides-Extra: docs
Requires-Dist: mistune==3.0.2; extra == 'docs'
Requires-Dist: mkdocs-autorefs<1.0.0,>=0.5.0; extra == 'docs'
Requires-Dist: mkdocs-git-authors-plugin<1.0.0,>=0.9.4; extra == 'docs'
Requires-Dist: mkdocs-git-revision-date-localized-plugin; extra == 'docs'
Requires-Dist: mkdocs-gitbook<1.0.0,>=0.0.1; extra == 'docs'
Requires-Dist: mkdocs-glightbox<1.0.0,>=0.4.0; extra == 'docs'
Requires-Dist: mkdocs-jupyter<1.0.0,>=0.25.1; extra == 'docs'
Requires-Dist: mkdocs-material-extensions<2.0.0,>=1.3.1; extra == 'docs'
Requires-Dist: mkdocs<2.0.0,>=1.4.0; extra == 'docs'
Requires-Dist: mkdocstrings[python]<1.0.0,>=0.25.2; extra == 'docs'
Requires-Dist: pymdown-extensions<11.0.0,>=10.14.3; extra == 'docs'
Provides-Extra: google
Requires-Dist: google-api-python-client<3.0.0,>=2.70.0; extra == 'google'
Requires-Dist: google-auth-oauthlib<2.0.0,>=1.0.0; extra == 'google'
Requires-Dist: gspread<6.0.0,>=5.0.0; extra == 'google'
Provides-Extra: lxml
Requires-Dist: lxml<6.0.0,>=5.3.0; extra == 'lxml'
Provides-Extra: oxi
Requires-Dist: oxrdflib<0.5.0,>=0.4.0; extra == 'oxi'
Requires-Dist: pyoxigraph<0.5.0,>=0.4.3; extra == 'oxi'
